CHANGELOG.txt
LICENSE.txt
MANIFEST.in
README.txt
setup.py
tvms/__init__.py
tvms/pic/__init__.py
tvmss.egg-info/PKG-INFO
tvmss.egg-info/SOURCES.txt
tvmss.egg-info/dependency_links.txt
tvmss.egg-info/top_level.txt