Metadata-Version: 2.1
Name: tvmss
Version: 0.0.14
Summary: Aboubakar
Home-page: 
Author: Boo4kin
Author-email: bkolyabi@gmail.com
License: MIT
Keywords: test
Classifier: Development Status :: 5 - Production/Stable
Classifier: Intended Audience :: Education
Classifier: Operating System :: Microsoft :: Windows :: Windows 10
Classifier: License :: OSI Approved :: MIT License
Classifier: Programming Language :: Python :: 3
License-File: LICENSE.txt
